flownetwork/__init__.py
flownetwork/flownetwork.py
flownetwork/flownetwork2.py
flownetwork-3.3.data/data/my_data/data_file.txt
sample/__init__.py
flownetwork-3.3.dist-info/LICENSE.txt
flownetwork-3.3.dist-info/METADATA
flownetwork-3.3.dist-info/WHEEL
flownetwork-3.3.dist-info/entry_points.txt
flownetwork-3.3.dist-info/top_level.txt
flownetwork-3.3.dist-info/RECORD
